{
    "Version":  "2026.07.17.83",
    "MenuChanges":  [
                        "Settings",
                        "Automation",
                        "Entities",
                        "Simulated Upgrades",
                        "Accessibility",
                        "Class Adjustment"
                    ],
    "Files":  [
                  {
                      "Path":  "NULLSCAPE/Main UI/master.luau",
                      "Menu":  [
                                   "Settings"
                               ],
                      "Sha256":  "6f6469579bbdc7172a2d9e227b7fc3f8b8da0ffd7622cc3890b3f9636f592d5e"
                  },
                  {
                      "Path":  "NULLSCAPE/Main UI/Updater.luau",
                      "Menu":  [
                                   "Settings"
                               ],
                      "Sha256":  "ebcdef92802f6033339e623f4416ba548e849f7bd89f2cf206294dcdc3c94a0d"
                  },
                  {
                      "Path":  "NULLSCAPE/Setting/tab.luau",
                      "Menu":  [
                                   "Settings"
                               ],
                      "Sha256":  "70d9b3192e36b249a11c92931f5a6f9eac1730ade393c21f1ee932c0f278fe2d"
                  },
                  {
                      "Path":  "NULLSCAPE/Core/Remote Registry.luau",
                      "Menu":  [
                                   "Settings"
                               ],
                      "Sha256":  "d644feb5d699f5401b420aeda323b76eaf82178feeef0fb3b85d0361f4e178f1"
                  },
                  {
                      "Path":  "NULLSCAPE/Core/Game State Context.luau",
                      "Menu":  [
                                   "Settings"
                               ],
                      "Sha256":  "3930e7d9d44f251090d0e2a5467b04feb88f8280306d563f5484725ebc7db06e"
                  },
                  {
                      "Path":  "NULLSCAPE/Automation/Gift Farm/Coordinator.luau",
                      "Menu":  [
                                   "Automation",
                                   "Gift Farm"
                               ],
                      "Sha256":  "7ffcd82a0ed3a8c723ff384b73de1366eaa40a418c3ec01f116e998f1fc6319b"
                  },
                  {
                      "Path":  "NULLSCAPE/Automation/Gift Farm/Run Policy.luau",
                      "Menu":  [
                                   "Automation",
                                   "Gift Farm"
                               ],
                      "Sha256":  "194684116d2f45e01adebcd8f66a6716823b7f55f948abee047e98448b48d323"
                  },
                  {
                      "Path":  "NULLSCAPE/Automation/Gift Farm/No Tracking.luau",
                      "Menu":  [
                                   "Automation",
                                   "Gift Farm"
                               ],
                      "Sha256":  "fb702ea35cd7fb665392d386853ffd2337f6f857a598eb6b38da47a663ec9bf6"
                  },
                  {
                      "Path":  "NULLSCAPE/Automation/Gift Farm/Immunity Handoff.luau",
                      "Menu":  [
                                   "Automation",
                                   "Gift Farm"
                               ],
                      "Sha256":  "ff8b74230b48daf141ec1b864fd9a4ea4da37ef8531f9584c96188fe91f77617"
                  },
                  {
                      "Path":  "NULLSCAPE/Automation/Gift Farm/Rule Overlay.luau",
                      "Menu":  [
                                   "Automation",
                                   "Gift Farm"
                               ],
                      "Sha256":  "fce22a28de083eb6ca3991ec5b585dce792803b60593f0e562035a69da6d076d"
                  },
                  {
                      "Path":  "NULLSCAPE/Automation/Gift Farm/MovementLease.luau",
                      "Menu":  [
                                   "Automation",
                                   "Gift Farm"
                               ],
                      "Sha256":  "0312a8494a273d72cbd4e89fe6d3906ceef5594b4d89ec6fdc16d6c6d5409ae5"
                  },
                  {
                      "Path":  "NULLSCAPE/Automation/Gift Farm/Transport.luau",
                      "Menu":  [
                                   "Automation",
                                   "Gift Farm"
                               ],
                      "Sha256":  "5bbb1fbe57f03124b552627adb0ad50237e02eb0cc3a2ae265ec8c7671a5cb99"
                  },
                  {
                      "Path":  "NULLSCAPE/Automation/Gift Farm/Context.luau",
                      "Menu":  [
                                   "Automation",
                                   "Gift Farm"
                               ],
                      "Sha256":  "9017524b77457d04e1f49b36e4bcf31ad550d9eac101cb1ca7f3957e21fff1a9"
                  },
                  {
                      "Path":  "NULLSCAPE/Automation/Gift Farm/Collector.luau",
                      "Menu":  [
                                   "Automation",
                                   "Gift Farm"
                               ],
                      "Sha256":  "f0bbcb927443da71f5d86bf0deba0161452253c02b8e1dc88c6a575cf4b743b2"
                  },
                  {
                      "Path":  "NULLSCAPE/Automation/Gift Farm/Beacon.luau",
                      "Menu":  [
                                   "Automation",
                                   "Gift Farm"
                               ],
                      "Sha256":  "d53100e32fa6ba4ae8a33efb6bbceee39a20ab8e62db6b9ff1f6969f983d0ca3"
                  },
                  {
                      "Path":  "NULLSCAPE/Automation/Gift Farm/Pipelined Collector/PipelinedCollector.luau",
                      "Menu":  [
                                   "Automation",
                                   "Gift Farm",
                                   "Pipelining"
                               ],
                      "Sha256":  "62fa1fdf8587e6ff6f615bdb3c1a54f7fd2be4f7dc3c1bdabc750d79826df6cd"
                  },
                  {
                      "Path":  "NULLSCAPE/Automation/controller.luau",
                      "Menu":  [
                                   "Automation"
                               ],
                      "Sha256":  "7066b31328d4593f2391d9087c5ffed910a692bf8714c391a939574bd18bf8fa"
                  },
                  {
                      "Path":  "NULLSCAPE/Entities/Kolona Auto QTE.luau",
                      "Menu":  [
                                   "Entities",
                                   "Kolona",
                                   "Auto QTE"
                               ],
                      "Sha256":  "8c4dff24cd852329637194b5d2f912fd47850b8f80e1953a727a6155abac77e6"
                  },
                  {
                      "Path":  "NULLSCAPE/Entities/Springer Auto Jump.luau",
                      "Menu":  [
                                   "Entities",
                                   "Springer",
                                   "Auto Jump"
                               ],
                      "Sha256":  "66a3129003456611611a3adca23dc008ac963bf9c6b5edd3fdc99747efad475b"
                  },
                  {
                      "Path":  "NULLSCAPE/Entities/Celestial Immunity.luau",
                      "Menu":  [
                                   "Entities",
                                   "Celestial"
                               ],
                      "Sha256":  "bc4e7986a0e7a08b4249411d67971bc5678363dc87c9c4cceb7e6cbd89fbe75c"
                  },
                  {
                      "Path":  "NULLSCAPE/Entities/Void Implosion Immunity.luau",
                      "Menu":  [
                                   "Entities",
                                   "Void Implosion"
                               ],
                      "Sha256":  "5b18078e6d180f8cb3b116828429bf8fc77efc18590e6fbd83633b7f1c2a1f62"
                  },
                  {
                      "Path":  "NULLSCAPE/Entities/controller.luau",
                      "Menu":  [
                                   "Entities"
                               ],
                      "Sha256":  "b9d778d90014ff82d7556a052dc1fc5ba56ea96996eabd592e56a2ffb846e181"
                  },
                  {
                      "Path":  "NULLSCAPE/Entities/RemoteBlocking.luau",
                      "Menu":  [
                                   "Entities"
                               ],
                      "Sha256":  "14fa322a9e85939118e2cf7b55cf7e824eacb36f63dc1be8178d82eb4d12edaa"
                  },
                  {
                      "Path":  "NULLSCAPE/Entities/Bell Immunity.luau",
                      "Menu":  [
                                   "Entities"
                               ],
                      "Sha256":  "8360d5a2d612b229efc631e56f0aadafda100386fb7bf59cf1b6ef804ac854a0"
                  },
                  {
                      "Path":  "NULLSCAPE/Entities/tab.luau",
                      "Menu":  [
                                   "Entities"
                               ],
                      "Sha256":  "479b2dcb69c306ad9293c155fd4ca8944671ddc6c6becbfaae6a6a466f50f85a"
                  },
                  {
                      "Path":  "NULLSCAPE/Simulated Upgrades/controller.luau",
                      "Menu":  [
                                   "Simulated Upgrades"
                               ],
                      "Sha256":  "39bc12940e37d4d307f97afddbd0b35e965b87ae5b1a2aed4e6b1e8ed2de4bfc"
                  },
                  {
                      "Path":  "NULLSCAPE/Simulated Upgrades/executor.luau",
                      "Menu":  [
                                   "Simulated Upgrades"
                               ],
                      "Sha256":  "459cb01da00b09cd67a0f386496095ef28be213e8f2766508a075ede79ddae01"
                  },
                  {
                      "Path":  "NULLSCAPE/Simulated Upgrades/Client Upgrade Injector.luau",
                      "Menu":  [
                                   "Simulated Upgrades"
                               ],
                      "Sha256":  "058db062e2d9999668a052b21a75aeac2d0ddeef147ed96b4157b2af839aa47d"
                  },
                  {
                      "Path":  "NULLSCAPE/Simulated Upgrades/Matrix Tetrahedron.luau",
                      "Menu":  [
                                   "Simulated Upgrades"
                               ],
                      "Sha256":  "1177d663a2c54d9f95061eed7107299e14e98a3c98b292a73d87195803113c4b"
                  },
                  {
                      "Path":  "NULLSCAPE/Simulated Upgrades/Advanced Gravity Coil.luau",
                      "Menu":  [
                                   "Simulated Upgrades"
                               ],
                      "Sha256":  "2b7e806d20cd80963658b8422d5d83e7136c13a82590b5246aca8eed63190035"
                  },
                  {
                      "Path":  "NULLSCAPE/Simulated Upgrades/Better Jump Pad.luau",
                      "Menu":  [
                                   "Simulated Upgrades"
                               ],
                      "Sha256":  "c58126bddfda208a9eda6ce6ca612d155b32e092a733490d3842184f44110c9b"
                  },
                  {
                      "Path":  "NULLSCAPE/Simulated Upgrades/Helmet.luau",
                      "Menu":  [
                                   "Simulated Upgrades"
                               ],
                      "Sha256":  "e429b4309f52e53cba8a81d6b3a3bfbb49871ae062b5788c0de7d75b675aea5b"
                  },
                  {
                      "Path":  "NULLSCAPE/Simulated Upgrades/Miniature Hourglass.luau",
                      "Menu":  [
                                   "Simulated Upgrades"
                               ],
                      "Sha256":  "eaa42e82d154ee4f032b6405f7664ad52c069485c4268a4c214db33dfc347576"
                  },
                  {
                      "Path":  "NULLSCAPE/Accessibility/Anti Bonk.luau",
                      "Menu":  [
                                   "Accessibility"
                               ],
                      "Sha256":  "cca0be09591ccbe2bf27ae0271b9287a32c21754a09f16f2351421c19e68b4f3"
                  },
                  {
                      "Path":  "NULLSCAPE/Accessibility/controller.luau",
                      "Menu":  [
                                   "Accessibility"
                               ],
                      "Sha256":  "0d55ef1b23ab426cf47077a460e928af61f5018021d5225b4c512a634ecffe69"
                  },
                  {
                      "Path":  "NULLSCAPE/Accessibility/Curse Visual Assist.luau",
                      "Menu":  [
                                   "Accessibility"
                               ],
                      "Sha256":  "320e47fb96c0aee6819ba34da75837ae76df99b0718c6d96ec76e99f5346ccbd"
                  },
                  {
                      "Path":  "NULLSCAPE/Accessibility/executor.luau",
                      "Menu":  [
                                   "Accessibility"
                               ],
                      "Sha256":  "7a8d2b1834c70a16e38ecf15d313c8887ee1b2dc95e0fe3bb057208756e50a52"
                  },
                  {
                      "Path":  "NULLSCAPE/Accessibility/GC.luau",
                      "Menu":  [
                                   "Accessibility"
                               ],
                      "Sha256":  "88b257943c9de8777ba22acfa27936caa766da432f1b65309cecb03a32b409a2"
                  },
                  {
                      "Path":  "NULLSCAPE/Accessibility/Momentum Guard.luau",
                      "Menu":  [
                                   "Accessibility"
                               ],
                      "Sha256":  "251f1d211d94aaff20534bc8db449cc1282adf5add8fef8550c59c9b0cc468e9"
                  },
                  {
                      "Path":  "NULLSCAPE/Accessibility/Physical Interaction Range.luau",
                      "Menu":  [
                                   "Accessibility"
                               ],
                      "Sha256":  "ceadc2c804fd1f9f2eac854c2a556b97dca005c0599bb29c7644b9818c869ad1"
                  },
                  {
                      "Path":  "NULLSCAPE/Accessibility/Rail Assist.luau",
                      "Menu":  [
                                   "Accessibility"
                               ],
                      "Sha256":  "22d195a47ea1d3e9d4c2d1e3f23eff2a3c447ad6bb66a830da4dde1fad893e90"
                  },
                  {
                      "Path":  "NULLSCAPE/Accessibility/Stamina Assist.luau",
                      "Menu":  [
                                   "Accessibility"
                               ],
                      "Sha256":  "0d6de1283d566ad6ef5f7f22b5e9f03ba621696e18f9599f0c923290dbf513de"
                  },
                  {
                      "Path":  "NULLSCAPE/Accessibility/tab.luau",
                      "Menu":  [
                                   "Accessibility"
                               ],
                      "Sha256":  "312e870a9c383b2a2693bf8b6120c4ecd13ff2bfb51a2bc145d98b7666029710"
                  },
                  {
                      "Path":  "NULLSCAPE/Accessibility/Grappler assistments/Adaptive Anchor Style.luau",
                      "Menu":  [
                                   "Accessibility"
                               ],
                      "Sha256":  "cc3592c2ae7c7fb19f999a565312a7c5ec9e5dff9c941c507a08131cac31b4ce"
                  },
                  {
                      "Path":  "NULLSCAPE/Accessibility/Grappler assistments/Ability Intent Context.luau",
                      "Menu":  [
                                   "Accessibility"
                               ],
                      "Sha256":  "5c67d042a283d638b15e7b6f0263a104a80fe23d4e64f164b203f41f939e7042"
                  },
                  {
                      "Path":  "NULLSCAPE/Accessibility/Grappler assistments/Anchor Bias Profile.luau",
                      "Menu":  [
                                   "Accessibility"
                               ],
                      "Sha256":  "d6895f4ca786bb880b67bf20cfd49b52c09ec4a6c494c831c122c7697749072f"
                  },
                  {
                      "Path":  "NULLSCAPE/Accessibility/Grappler assistments/Anchor Preference Profile.luau",
                      "Menu":  [
                                   "Accessibility"
                               ],
                      "Sha256":  "a9952533cf96803d2559377321abfb24ded461a666b40440e9c34e01f21e068a"
                  },
                  {
                      "Path":  "NULLSCAPE/Accessibility/Grappler assistments/Assist Confidence Gate.luau",
                      "Menu":  [
                                   "Accessibility"
                               ],
                      "Sha256":  "d992e1e3c79688262d03ffd4b5f463fcbe6f2d3e29635964f8d589f60c6b91d4"
                  },
                  {
                      "Path":  "NULLSCAPE/Accessibility/Grappler assistments/Bad Anchor Memory.luau",
                      "Menu":  [
                                   "Accessibility"
                               ],
                      "Sha256":  "0693dccccbe5e3b796c7fe74b997b33eb90a409cc3919b3cd05af5185aff30f9"
                  },
                  {
                      "Path":  "NULLSCAPE/Accessibility/Grappler assistments/Biome Tuning.luau",
                      "Menu":  [
                                   "Accessibility"
                               ],
                      "Sha256":  "dd6ced7d0101599d39869c6f20e24de3aedd340aca648d4a4f35b22375c6e106"
                  },
                  {
                      "Path":  "NULLSCAPE/Accessibility/Grappler assistments/Cast Safety Check.luau",
                      "Menu":  [
                                   "Accessibility"
                               ],
                      "Sha256":  "68a91a6bf94cfc9b0a52860f9e3e2b4e9854dcbb98dd6a4a49be4fa192f7686d"
                  },
                  {
                      "Path":  "NULLSCAPE/Accessibility/Grappler assistments/Deferred Aim Cast.luau",
                      "Menu":  [
                                   "Accessibility"
                               ],
                      "Sha256":  "9dc56bb9889e9879849aefd72a2fbdcc4394bb85ff61c308d2f3160d04d27560"
                  },
                  {
                      "Path":  "NULLSCAPE/Accessibility/Grappler assistments/Entity Intent Context.luau",
                      "Menu":  [
                                   "Accessibility"
                               ],
                      "Sha256":  "627f647d0132a0ca6cacd2dd8aecbb8bdaf181bbb210e95a2808ba7acd4d11dd"
                  },
                  {
                      "Path":  "NULLSCAPE/Accessibility/Grappler assistments/Fail Feedback Loop.luau",
                      "Menu":  [
                                   "Accessibility"
                               ],
                      "Sha256":  "0ffc0150c1991317c32df2b925373eb2b65dd6216a2fc775eaf26ad326ce0055"
                  },
                  {
                      "Path":  "NULLSCAPE/Accessibility/Grappler assistments/Grapple Assist.luau",
                      "Menu":  [
                                   "Accessibility"
                               ],
                      "Sha256":  "f19aba808575a8b1c33499a9e6d25bcb376aae20cb598aa27dc47e5e79dd7a18"
                  },
                  {
                      "Path":  "NULLSCAPE/Accessibility/Grappler assistments/Intent Resolver.luau",
                      "Menu":  [
                                   "Accessibility"
                               ],
                      "Sha256":  "b86a29d68e143a6c56cca639601e277532668aae563e78d3fb6d2ba405a6f5e2"
                  },
                  {
                      "Path":  "NULLSCAPE/Accessibility/Grappler assistments/Intent Target Gate.luau",
                      "Menu":  [
                                   "Accessibility"
                               ],
                      "Sha256":  "7332ce542a07258c249081e6ae8181e476c940276737533617aa0284f57250ca"
                  },
                  {
                      "Path":  "NULLSCAPE/Accessibility/Grappler assistments/Landing Predictor.luau",
                      "Menu":  [
                                   "Accessibility"
                               ],
                      "Sha256":  "06f44cf56d62d50b317c81ee8f63c3be0e5ce8d0a8171f92106e6fdd26a627a1"
                  },
                  {
                      "Path":  "NULLSCAPE/Accessibility/Grappler assistments/Momentum Intent Bridge.luau",
                      "Menu":  [
                                   "Accessibility"
                               ],
                      "Sha256":  "2a6a954d26e2404c0d2e3b858180eac61f1069cb2d6db6ed59a85895a94e0e49"
                  },
                  {
                      "Path":  "NULLSCAPE/Accessibility/Grappler assistments/Pilot State.luau",
                      "Menu":  [
                                   "Accessibility"
                               ],
                      "Sha256":  "a1f2d43df09b258778eb5ad704f429d53974457750fcabee62898edd6bcab1a7"
                  },
                  {
                      "Path":  "NULLSCAPE/Accessibility/Grappler assistments/Rail Snap Assist.luau",
                      "Menu":  [
                                   "Accessibility"
                               ],
                      "Sha256":  "c88a587b8d02f9efa2662b6c50756f0af7c452ba5844024b4a40861441734b6a"
                  },
                  {
                      "Path":  "NULLSCAPE/Accessibility/Grappler assistments/Reel Release Advisor.luau",
                      "Menu":  [
                                   "Accessibility"
                               ],
                      "Sha256":  "cdeb1874af5759a1d608ac283681d38f969851107c9fcee2d79168e08090b795"
                  },
                  {
                      "Path":  "NULLSCAPE/Accessibility/Grappler assistments/Release Timing Helper.luau",
                      "Menu":  [
                                   "Accessibility"
                               ],
                      "Sha256":  "9361e84bf620bd0f88b081644c3f0411f4afde0b84e330f1b80197a89eab2308"
                  },
                  {
                      "Path":  "NULLSCAPE/Accessibility/Grappler assistments/Secondary Cast.luau",
                      "Menu":  [
                                   "Accessibility"
                               ],
                      "Sha256":  "c9dfa0ba08250e688c3ab39b0f5f0c584dc34cf28b58a884428cf59bacfee4e3"
                  },
                  {
                      "Path":  "NULLSCAPE/Accessibility/Grappler assistments/Special Anchors.luau",
                      "Menu":  [
                                   "Accessibility"
                               ],
                      "Sha256":  "08c90c4e444f16bbb99e07738677942d3b9640fa09898f4df3964eefce69cb96"
                  },
                  {
                      "Path":  "NULLSCAPE/Accessibility/Grappler assistments/Targeting.luau",
                      "Menu":  [
                                   "Accessibility"
                               ],
                      "Sha256":  "b538de77fc3c0d73780b96cbde909f44771267d2d04efe5c8aecb9b4851fa0bf"
                  },
                  {
                      "Path":  "NULLSCAPE/Accessibility/Grappler assistments/Technique Arbiter.luau",
                      "Menu":  [
                                   "Accessibility"
                               ],
                      "Sha256":  "6df600c336b325e4e67b6886d18da7e98b3c2b274ac9775548c56ade486e593b"
                  },
                  {
                      "Path":  "NULLSCAPE/Accessibility/Grappler assistments/Technique Decision Layer.luau",
                      "Menu":  [
                                   "Accessibility"
                               ],
                      "Sha256":  "aaa09fd7d571ce42179af2821bf5f2a912871b3f6a4182e9673853ba95b38e01"
                  },
                  {
                      "Path":  "NULLSCAPE/Accessibility/Grappler assistments/Upgrade Gate.luau",
                      "Menu":  [
                                   "Accessibility"
                               ],
                      "Sha256":  "ca54646d6df04e55e6e233757d62af55f6ef4da27e583e3bb65ae0397d76c526"
                  },
                  {
                      "Path":  "NULLSCAPE/Accessibility/Grappler assistments/Map Context/Anchor Memory.luau",
                      "Menu":  [
                                   "Accessibility"
                               ],
                      "Sha256":  "b14cd7986bb1ac16f52c7b2181bd8e35b173aa4216f9796e36a5fdbaac099555"
                  },
                  {
                      "Path":  "NULLSCAPE/Accessibility/Grappler assistments/Map Context/Rail Memory Proxy.luau",
                      "Menu":  [
                                   "Accessibility"
                               ],
                      "Sha256":  "937ff20eee710d343728a80566c3739a275410b9b7e32917ec6f9408df988610"
                  },
                  {
                      "Path":  "NULLSCAPE/Accessibility/Grappler assistments/Map Context/Rail Memory.luau",
                      "Menu":  [
                                   "Accessibility"
                               ],
                      "Sha256":  "76e41d09504dc278d2aca1fece712aa159b88b007a50cee1410a253d2adf0dee"
                  },
                  {
                      "Path":  "NULLSCAPE/Accessibility/Grappler assistments/Map Context/Ray Sampler.luau",
                      "Menu":  [
                                   "Accessibility"
                               ],
                      "Sha256":  "00165fb942795f829d29804035b2d4a6a49c43ad58e69f728c6017fae05c53ed"
                  },
                  {
                      "Path":  "NULLSCAPE/Accessibility/Grappler assistments/Map Context/Spatial Index.luau",
                      "Menu":  [
                                   "Accessibility"
                               ],
                      "Sha256":  "893eca26f3d679f3bfec202110f4c2e4f1bfd7d3de494fb1044c68635e639d19"
                  },
                  {
                      "Path":  "NULLSCAPE/Accessibility/Grappler assistments/Map Context/Terrain Memory.luau",
                      "Menu":  [
                                   "Accessibility"
                               ],
                      "Sha256":  "995ebeff6c9f23c6283054c44175c399a180858e4cef3a35819a92e4e2db81d9"
                  },
                  {
                      "Path":  "NULLSCAPE/Accessibility/Grappler assistments/Technique/Bell Contact Assist.luau",
                      "Menu":  [
                                   "Accessibility"
                               ],
                      "Sha256":  "988fa06e7022a5c9f239d7cd6c30f210f257e91f8cb8e44e35671147fa50ead6"
                  },
                  {
                      "Path":  "NULLSCAPE/Accessibility/Grappler assistments/Technique/Grapple Dodge.luau",
                      "Menu":  [
                                   "Accessibility"
                               ],
                      "Sha256":  "d52550629337f4d175e4d940fcb6d307fa233de76d3db110491259c4e71059d0"
                  },
                  {
                      "Path":  "NULLSCAPE/Accessibility/Grappler assistments/Technique/SharkVoid.luau",
                      "Menu":  [
                                   "Accessibility"
                               ],
                      "Sha256":  "b4b64e30c7e1beda803e6ab19f883751faa6c4a9b5c47b1c1b37bf2572dd72d5"
                  },
                  {
                      "Path":  "NULLSCAPE/Accessibility/Grappler assistments/Technique/Reel Saver/init.luau",
                      "Menu":  [
                                   "Accessibility"
                               ],
                      "Sha256":  "18b1405aeb5b86fe35c6daf3c01fa59d2b0335e9648ca00587c9c04182669daa"
                  },
                  {
                      "Path":  "NULLSCAPE/Accessibility/Grappler assistments/Technique/Reel Saver/Terrain Query.luau",
                      "Menu":  [
                                   "Accessibility"
                               ],
                      "Sha256":  "742bdfd6e2b1583582522204cf62f7a5dec3c4e5210ad2b8aa131d152a1c823e"
                  },
                  {
                      "Path":  "NULLSCAPE/Accessibility/Movement Context/Momentum Memory.luau",
                      "Menu":  [
                                   "Accessibility"
                               ],
                      "Sha256":  "c380b712b82687dad884dc1c4671e6e0d889e5197487b19c925c6d9e4eddc8a9"
                  },
                  {
                      "Path":  "NULLSCAPE/Accessibility/Threat Context/Dodge Planner.luau",
                      "Menu":  [
                                   "Accessibility"
                               ],
                      "Sha256":  "873f34bfaf686792d30fbd192ad0a6ec47a7d7268a91f712b36e7ce95d5eb2ea"
                  },
                  {
                      "Path":  "NULLSCAPE/Accessibility/Threat Context/Enemy Memory.luau",
                      "Menu":  [
                                   "Accessibility"
                               ],
                      "Sha256":  "2d5a164d07c3dc715f241bb41a7369f80d68e577c7fd9501dbe784023c312608"
                  },
                  {
                      "Path":  "NULLSCAPE/Class Adjustment/Control.luau",
                      "Menu":  [
                                   "Class Adjustment"
                               ],
                      "Sha256":  "5d91b566e82d1714f0725ef567e4d43deab329e48603c701c9e75a8b78e08077"
                  },
                  {
                      "Path":  "NULLSCAPE/Class Adjustment/Executor.luau",
                      "Menu":  [
                                   "Class Adjustment"
                               ],
                      "Sha256":  "f9bb44a61e223ed289d30bd99e5dfdad833840f8bc1179bea3be38343a10a4fb"
                  },
                  {
                      "Path":  "NULLSCAPE/Class Adjustment/GC.luau",
                      "Menu":  [
                                   "Class Adjustment"
                               ],
                      "Sha256":  "4bcc6fc792e429a819fcce6172a0912b7b23e77ac6e13a5b37f84ba8a4ab6ad2"
                  },
                  {
                      "Path":  "NULLSCAPE/Class Adjustment/tab.luau",
                      "Menu":  [
                                   "Class Adjustment"
                               ],
                      "Sha256":  "04e267f3377727d69c377823e4f316df48b42a52275c4f8fecd8338541de8441"
                  },
                  {
                      "Path":  "NULLSCAPE/Class Adjustment/Charger/Tripmine Assist.luau",
                      "Menu":  [
                                   "Class Adjustment"
                               ],
                      "Sha256":  "aadd8506ff4aae68d32e6f52614517ef9a8e35588652b6c18fa3f2d5508fa37a"
                  },
                  {
                      "Path":  "NULLSCAPE/Class Adjustment/Charger/Steering Assist.luau",
                      "Menu":  [
                                   "Class Adjustment"
                               ],
                      "Sha256":  "7bb999f464f82d1ba22d2626f2aa1f31cff953771dfb19ea0d873469c0810d39"
                  },
                  {
                      "Path":  "NULLSCAPE/Class Adjustment/Charger/Charge Collision Guard.luau",
                      "Menu":  [
                                   "Class Adjustment"
                               ],
                      "Sha256":  "944809af167e8c75361d122f2e3c6341525b8bfa30a7e79bf8b14974813f6947"
                  },
                  {
                      "Path":  "NULLSCAPE/Class Adjustment/Charger/Charger Assist Context.luau",
                      "Menu":  [
                                   "Class Adjustment"
                               ],
                      "Sha256":  "1e5370e8d1da5ea0f7600b7e66ec050da739ffcc73c34b397c374d334807e790"
                  },
                  {
                      "Path":  "NULLSCAPE/Class Adjustment/Charger/Charger Assist Hooks.luau",
                      "Menu":  [
                                   "Class Adjustment"
                               ],
                      "Sha256":  "b3c704fc3597e0da1642dc8024ec495ba34abe421e6d67df6a6cfa3ffd48101a"
                  },
                  {
                      "Path":  "NULLSCAPE/Class Adjustment/Charger/Charger Assist Suite.luau",
                      "Menu":  [
                                   "Class Adjustment"
                               ],
                      "Sha256":  "c4c97c3cd0ec31e2541d40e21308e941522bbb060045b4a728df21b645589e0a"
                  },
                  {
                      "Path":  "NULLSCAPE/Class Adjustment/Grappler/Grapple Air Control.luau",
                      "Menu":  [
                                   "Class Adjustment"
                               ],
                      "Sha256":  "f6074d1eab0e4a19b64278c6feafa10d9e118fa3b0bcf56a29f874847510f3c4"
                  },
                  {
                      "Path":  "NULLSCAPE/Class Adjustment/Grappler/Grapple Hook Cast Speed.luau",
                      "Menu":  [
                                   "Class Adjustment"
                               ],
                      "Sha256":  "138a750d8df7b9e68dd14aaa8e60af6eaa05fbd7d5c111f111b545e08775b68a"
                  },
                  {
                      "Path":  "NULLSCAPE/Class Adjustment/Grappler/Grapple Range.luau",
                      "Menu":  [
                                   "Class Adjustment"
                               ],
                      "Sha256":  "20b9f2d9c3b5b5e0ad14400172094e371ba702e39b2751da5cfdf8dabbee7e6d"
                  },
                  {
                      "Path":  "NULLSCAPE/Class Adjustment/Grappler/Grapple Recovery.luau",
                      "Menu":  [
                                   "Class Adjustment"
                               ],
                      "Sha256":  "03b90864337daaf5acf0ea5d865f3d008fa30600ba0120ac6ca65c5149b6881d"
                  },
                  {
                      "Path":  "NULLSCAPE/Class Adjustment/Grappler/Grapple Reel Pull.luau",
                      "Menu":  [
                                   "Class Adjustment"
                               ],
                      "Sha256":  "917b4c6beab0c3cefb3cc7a3c7942ed7e19d63399b3b974312947c1dd1870f5c"
                  },
                  {
                      "Path":  "NULLSCAPE/Class Adjustment/Grappler/Grapple Void Cast Assist.luau",
                      "Menu":  [
                                   "Class Adjustment"
                               ],
                      "Sha256":  "30b3259209e0c0c577b1278d0471b724ed7218c77d7d99acf42789843b239ced"
                  },
                  {
                      "Path":  "NULLSCAPE/Class Adjustment/Grappler/SharkTail Cooldown.luau",
                      "Menu":  [
                                   "Class Adjustment"
                               ],
                      "Sha256":  "10bde6a43f48c782aaeb599de3c10a0c03e6658c8f49d578e0b46105f32cbb0f"
                  },
                  {
                      "Path":  "NULLSCAPE/Class Adjustment/Grappler/SharkTail Pull.luau",
                      "Menu":  [
                                   "Class Adjustment"
                               ],
                      "Sha256":  "a96f0eb342233637cd82f62a67caeeae9286239d771c9920e4af330910ff31cf"
                  },
                  {
                      "Path":  "NULLSCAPE/Automation/Auto Choose Things.luau",
                      "Menu":  [
                                   "Automation"
                               ],
                      "Sha256":  "5c6dfafa71d0dbf021247de2f7c1efe7981ad8319635f4c63451bf19374639a3"
                  },
                  {
                      "Path":  "NULLSCAPE/Automation/executor.luau",
                      "Menu":  [
                                   "Automation"
                               ],
                      "Sha256":  "a80c447c595393009c919995bf3320fa4bc1b04ffbbf73e2ca40c43eeaae9178"
                  },
                  {
                      "Path":  "NULLSCAPE/Automation/GC.luau",
                      "Menu":  [
                                   "Automation"
                               ],
                      "Sha256":  "ed17681669f42a3fc2b196804545153a1b8dad52edee71d6d1d8a100f4e0719b"
                  },
                  {
                      "Path":  "NULLSCAPE/Automation/Gift Farm.luau",
                      "Menu":  [
                                   "Automation"
                               ],
                      "Sha256":  "1be31e19c9b26d075da99873d55218c9fe6e2336b30112ff7cdb32a99fa29ad3"
                  },
                  {
                      "Path":  "NULLSCAPE/Automation/Pylon Activator.luau",
                      "Menu":  [
                                   "Automation"
                               ],
                      "Sha256":  "06205665d87a716fb7946ad0de8d50a8a7b0adbadaa004b260ffe63dc4376f8e"
                  },
                  {
                      "Path":  "NULLSCAPE/Automation/tab.luau",
                      "Menu":  [
                                   "Automation"
                               ],
                      "Sha256":  "861b79f2d7f86c7133ce3bc29c4fc716017e3ae37fa5c70d1b93b993929aec57"
                  },
                  {
                      "Path":  "NULLSCAPE/Automation/Gift Farm/Altar.luau",
                      "Menu":  [
                                   "Automation"
                               ],
                      "Sha256":  "1f373defb384d8d66e6eda9834ff85f1af9592a17c1ad5f15f0783db2e0c7648"
                  },
                  {
                      "Path":  "NULLSCAPE/Automation/Gift Farm/Cluster Planner.luau",
                      "Menu":  [
                                   "Automation"
                               ],
                      "Sha256":  "8131a1bcaecf8184403ef951ba3c118eb41c6118b6c1e91f6fbd153c7047808e"
                  },
                  {
                      "Path":  "NULLSCAPE/Automation/Gift Farm/Collapse.luau",
                      "Menu":  [
                                   "Automation"
                               ],
                      "Sha256":  "332076aad615f88a3f2c15bbabe919f03e0dcc6c1de2962760e1797b395a84da"
                  },
                  {
                      "Path":  "NULLSCAPE/Automation/Gift Farm/Distance.luau",
                      "Menu":  [
                                   "Automation"
                               ],
                      "Sha256":  "8dd8d9c0a64ee7d94395ff151f96c77f5c328d737e1ef8565f4702339acfd033"
                  },
                  {
                      "Path":  "NULLSCAPE/Automation/Gift Farm/Golden Wait.luau",
                      "Menu":  [
                                   "Automation"
                               ],
                      "Sha256":  "a4e3db69ff11da53245e2f4d96b7a97afcbc9af526563994168a367496e16b15"
                  },
                  {
                      "Path":  "NULLSCAPE/Automation/Gift Farm/Medal.luau",
                      "Menu":  [
                                   "Automation"
                               ],
                      "Sha256":  "4ac33473a06bca62059d11e61a9867b35258681cad6dac8b214d567ae6ccdf11"
                  },
                  {
                      "Path":  "NULLSCAPE/Automation/Gift Farm/Mode Isolation.luau",
                      "Menu":  [
                                   "Automation"
                               ],
                      "Sha256":  "c1aa235836639333a0067bfd485e0ac180ef3dee53ba1c619f23690504b9e063"
                  },
                  {
                      "Path":  "NULLSCAPE/Automation/Gift Farm/Progress.luau",
                      "Menu":  [
                                   "Automation"
                               ],
                      "Sha256":  "8da4399da9d9c2c604455e638a05c1022dfada23ec1ee799a821c689a1676740"
                  },
                  {
                      "Path":  "NULLSCAPE/Automation/Gift Farm/Scanner.luau",
                      "Menu":  [
                                   "Automation"
                               ],
                      "Sha256":  "1c745654ed9e15501962de080f011946c87655c3f83e1861a1b8a53fe7ffd7e0"
                  },
                  {
                      "Path":  "NULLSCAPE/Entities/executor.luau",
                      "Menu":  [
                                   "Entities"
                               ],
                      "Sha256":  "8a53c3bc75540481b8693e4b84b154707d2cd3153e2726260cad0f047ffefd7a"
                  },
                  {
                      "Path":  "NULLSCAPE/Entities/GC.luau",
                      "Menu":  [
                                   "Entities"
                               ],
                      "Sha256":  "c306fcfa344fa99c84af998700d351fe8ed342732cac6d967cd90569ac515dc3"
                  },
                  {
                      "Path":  "NULLSCAPE/Entities/HuskEvasion.luau",
                      "Menu":  [
                                   "Entities"
                               ],
                      "Sha256":  "f3a90eb5a5273589cee565ed6a4e885aa4e6666d4df2907bd45e5ae11f9165a8"
                  },
                  {
                      "Path":  "NULLSCAPE/Entities/SpecialImmunity.luau",
                      "Menu":  [
                                   "Entities"
                               ],
                      "Sha256":  "fdc831e05f7740640043474e00e0bc30c23f0114cc9866c58063f3236eed9ffc"
                  },
                  {
                      "Path":  "NULLSCAPE/Entities/StatusImmunity.luau",
                      "Menu":  [
                                   "Entities"
                               ],
                      "Sha256":  "924291f3df5b81345a99605ca35b157b22e27ae724360143620f972d810c79f7"
                  },
                  {
                      "Path":  "NULLSCAPE/Entities/TouchInterest.luau",
                      "Menu":  [
                                   "Entities"
                               ],
                      "Sha256":  "c2c305944c9fbdc76de7c60b0ca59136c54ca26181eab0761fe082f506e9c897"
                  },
                  {
                      "Path":  "NULLSCAPE/Simulated Upgrades/Defuse Kits.luau",
                      "Menu":  [
                                   "Simulated Upgrades"
                               ],
                      "Sha256":  "a792e9bd33652b9a146982687e97e73c81b8164e0a1ac47a77bf8e60940c4d7e"
                  },
                  {
                      "Path":  "NULLSCAPE/Simulated Upgrades/GC.luau",
                      "Menu":  [
                                   "Simulated Upgrades"
                               ],
                      "Sha256":  "f32d3b87b41c9126006b5748475028eca92ce0733e10c2725044ec2bdff97e73"
                  },
                  {
                      "Path":  "NULLSCAPE/Simulated Upgrades/Grace Wings.luau",
                      "Menu":  [
                                   "Simulated Upgrades"
                               ],
                      "Sha256":  "75f40b986357819b57f3a83de16c951466ea72729f20ed8682c30d43099a5cd0"
                  },
                  {
                      "Path":  "NULLSCAPE/Simulated Upgrades/Magnet logic.luau",
                      "Menu":  [
                                   "Simulated Upgrades"
                               ],
                      "Sha256":  "cc38770092bfa575144b9d48d92d553389c02634ba7d5b361ef9b4e36d6cbf04"
                  },
                  {
                      "Path":  "NULLSCAPE/Simulated Upgrades/Radar logic.luau",
                      "Menu":  [
                                   "Simulated Upgrades"
                               ],
                      "Sha256":  "39f08cc6a55364f0314c0e999a25a4e32478b0c00da3a2cea7e1f1f4b8971902"
                  },
                  {
                      "Path":  "NULLSCAPE/Simulated Upgrades/Speed Buffs.luau",
                      "Menu":  [
                                   "Simulated Upgrades"
                               ],
                      "Sha256":  "05e16f85d9ffccc79cdbc6de300e2d825487bb83916b1f113419f80073ef2b5f"
                  },
                  {
                      "Path":  "NULLSCAPE/Simulated Upgrades/Air Jumps.luau",
                      "Menu":  [
                                   "Simulated Upgrades"
                               ],
                      "Sha256":  "d3914f08adfc0b073510eb2a61ce6481b0aed9bb0ce412b32c6189b5b160906e"
                  },
                  {
                      "Path":  "NULLSCAPE/Simulated Upgrades/tab.luau",
                      "Menu":  [
                                   "Simulated Upgrades"
                               ],
                      "Sha256":  "d8eff842a3b584b5a2deaa541c94204db690c60c6606b4adc5d6ed6028100fe8"
                  },
                  {
                      "Path":  "NULLSCAPE/Class Adjustment/Grappler/Grapple Catapult Boost.luau",
                      "Menu":  [
                                   "Class Adjustment"
                               ],
                      "Sha256":  "10f2d9413ae5b1001579c6681dae1f3d832d948a16121418ec79854cb112a423"
                  },
                  {
                      "Path":  "NULLSCAPE/Class Adjustment/Grappler/Grapple Momentum Transfer.luau",
                      "Menu":  [
                                   "Class Adjustment"
                               ],
                      "Sha256":  "b33c92d57aed2d674bd10e83b1d1c1907d0a96c68ad6ab8160d59ac2c4f9326b"
                  },
                  {
                      "Path":  "NULLSCAPE/Accessibility/Grappler assistments/Aim Target Lock.luau",
                      "Menu":  "Accessibility",
                      "Sha256":  "28d762d02d91d0da082d9623ad876abb66507c5fccea8baee9254871dc857c98"
                  },
                  {
                      "Path":  "NULLSCAPE/Accessibility/Grappler assistments/Cast Decision Gateway.luau",
                      "Menu":  "Accessibility",
                      "Sha256":  "de28099ec372f8d1fa53ae525c2af4997bf3f330b793d18b462e5fbcec761de9"
                  },
                  {
                      "Path":  "NULLSCAPE/Accessibility/Grappler assistments/Cast Transaction.luau",
                      "Menu":  "Accessibility",
                      "Sha256":  "637d1262740ea2cc628a73201912d59d1e3969a1127c1a03d74980c3b1c528b3"
                  },
                  {
                      "Path":  "NULLSCAPE/Accessibility/Grappler assistments/Grapple State Adapter.luau",
                      "Menu":  "Accessibility",
                      "Sha256":  "b2810d5affbe4025039e3fd37b6622619d8c7e7e7bad3cbc3a006c64f7abd2d3"
                  },
                  {
                      "Path":  "NULLSCAPE/Accessibility/Grappler assistments/Native Context Sync.luau",
                      "Menu":  "Accessibility",
                      "Sha256":  "597612cd5e667f3fd7da21a7feca378b79a9841c14d2a697c2dbfdeaaddfe4ab"
                  },
                  {
                      "Path":  "NULLSCAPE/Accessibility/Grappler assistments/Performance Budget.luau",
                      "Menu":  "Accessibility",
                      "Sha256":  "a4946b24c75360da12fa12e2e001d33d75bc9be67a5f47a652fe89e403170007"
                  },
                  {
                      "Path":  "NULLSCAPE/Accessibility/Grappler assistments/Player Intent State.luau",
                      "Menu":  "Accessibility",
                      "Sha256":  "9ece9874d806e47e927578c4f55de022a41e89a0c6b88e577d437962d017f319"
                  },
                  {
                      "Path":  "NULLSCAPE/Accessibility/Grappler assistments/Release Policy.luau",
                      "Menu":  "Accessibility",
                      "Sha256":  "40145a78c75f3ebdd70c4f25568b65313b511f95065f55af2b46a2698db96662"
                  },
                  {
                      "Path":  "NULLSCAPE/Setting/Destroy Logic.luau",
                      "Menu":  [
                                   "Settings"
                               ],
                      "Sha256":  "1cc38bc414aea28a1cdf72ea708dc4400d676c24a7403819d4c158dbefc47544"
                  },
                  {
                      "Path":  "NULLSCAPE/Core/Class Context.luau",
                      "Sha256":  "730362d3f18a7be8aaeb3a1024072d95dffa615f7c4224371c14029d28db6c73"
                  },
                  {
                      "Path":  "NULLSCAPE/Setting/FPS Boost.luau",
                      "Sha256":  "5b116b48dc5fefbcc110fd919fe0aab5da99eba06f5dd6ce5a5c0ae7c6dee0c4"
                  },
                  {
                      "Path":  "NULLSCAPE/Setting/Ultimate FPS Booster.luau",
                      "Menu":  [
                                   "Settings"
                               ],
                      "Sha256":  "78f8888d72f62daf4d30d8ba12a609bdeb2080bed2c4976efd52ac2a7028363e"
                  },
                  {
                      "Path":  "NULLSCAPE/Setting/Character Actions.luau",
                      "Menu":  [
                                   "Settings"
                               ],
                      "Sha256":  "347b99a69db2ea1c524fc8588d6ee274ebb6530cb980b96b441000417a4acc37"
                  },
                  {
                      "Path":  "NULLSCAPE/Entities/Cadence Status.luau",
                      "Menu":  [
                                   "Entities"
                               ],
                      "Sha256":  "1226e2c233c616467cb0d19806efc37668776e659c23dc3c4ddc82886e1ae496"
                  },
                  {
                      "Path":  "NULLSCAPE/Entities/Operator Auto Disable.luau",
                      "Menu":  [
                                   "Entities"
                               ],
                      "Sha256":  "aeec562b3d11de21645b43876a27b4f1e74a891e7e6666faa1214cba8666b764"
                  },
                  {
                      "Path":  "NULLSCAPE/Entities/Razorbloom Auto Disable.luau",
                      "Menu":  [
                                   "Entities"
                               ],
                      "Sha256":  "bde5360faa3981da1aaea45e069ab2e3765bfd8fcdeed9573ebf5040161fd357"
                  }
              ]
}
